<annotation>
	<folder>n04081281</folder>
	<filename>n04081281_32250</filename>
	<source>
		<database>ImageNet database</database>
	</source>
	<size>
		<width>322</width>
		<height>500</height>
		<depth>3</depth>
	</size>
	<segmented>0</segmented>
	<object>
		<name>n13104059</name>
		<pose>Unspecified</pose>
		<truncated>0</truncated>
		<difficult>0</difficult>
		<bndbox>
			<xmin>57</xmin>
			<ymin>314</ymin>
			<xmax>256</xmax>
			<ymax>460</ymax>
		</bndbox>
	</object>
	<object>
		<name>n13104059</name>
		<pose>Unspecified</pose>
		<truncated>0</truncated>
		<difficult>0</difficult>
		<bndbox>
			<xmin>0</xmin>
			<ymin>357</ymin>
			<xmax>76</xmax>
			<ymax>421</ymax>
		</bndbox>
	</object>
	<object>
		<name>n00017222</name>
		<pose>Unspecified</pose>
		<truncated>0</truncated>
		<difficult>0</difficult>
		<bndbox>
			<xmin>58</xmin>
			<ymin>337</ymin>
			<xmax>167</xmax>
			<ymax>463</ymax>
		</bndbox>
	</object>
	<object>
		<name>n00017222</name>
		<pose>Unspecified</pose>
		<truncated>0</truncated>
		<difficult>0</difficult>
		<bndbox>
			<xmin>149</xmin>
			<ymin>335</ymin>
			<xmax>228</xmax>
			<ymax>427</ymax>
		</bndbox>
	</object>
	<object>
		<name>n00017222</name>
		<pose>Unspecified</pose>
		<truncated>0</truncated>
		<difficult>0</difficult>
		<bndbox>
			<xmin>0</xmin>
			<ymin>349</ymin>
			<xmax>72</xmax>
			<ymax>426</ymax>
		</bndbox>
	</object>
	<object>
		<name>n00017222</name>
		<pose>Unspecified</pose>
		<truncated>0</truncated>
		<difficult>0</difficult>
		<bndbox>
			<xmin>3</xmin>
			<ymin>358</ymin>
			<xmax>55</xmax>
			<ymax>395</ymax>
		</bndbox>
	</object>
	<object>
		<name>n04272054</name>
		<pose>Unspecified</pose>
		<truncated>0</truncated>
		<difficult>0</difficult>
		<bndbox>
			<xmin>216</xmin>
			<ymin>400</ymin>
			<xmax>231</xmax>
			<ymax>406</ymax>
		</bndbox>
	</object>
</annotation>